swimlane_records_updater/SruRecords.py
swimlane_records_updater/__init__.py
swimlane_records_updater-2018.10.18.1.dist-info/LICENSE
swimlane_records_updater-2018.10.18.1.dist-info/METADATA
swimlane_records_updater-2018.10.18.1.dist-info/WHEEL
swimlane_records_updater-2018.10.18.1.dist-info/top_level.txt
swimlane_records_updater-2018.10.18.1.dist-info/RECORD
