Metadata-Version: 2.1
Name: swimlane-records-updater
Version: 2018.10.18.1
Summary: Common Record Updater for Swimlane apps
Home-page: https://github.com/jeremymcrews/swimlane_record_updater
Author: Jeremy M Crews
Author-email: jeremy.m.crews@gmail.com
License: UNKNOWN
Platform: UNKNOWN
Classifier: Programming Language :: Python :: 2
Classifier: License :: OSI Approved :: MIT License
Classifier: Operating System :: OS Independent
Requires-Dist: swimlane
Requires-Dist: ConfigParser
Requires-Dist: slackclient
